pycommit/__init__.py
pycommit/__main__.py
pycommit/pycommit.py
PyCommit-0.1.0.dist-info/LICENSE
PyCommit-0.1.0.dist-info/METADATA
PyCommit-0.1.0.dist-info/WHEEL
PyCommit-0.1.0.dist-info/entry_points.txt
PyCommit-0.1.0.dist-info/top_level.txt
PyCommit-0.1.0.dist-info/RECORD
